setup.py
NoteBookForMinio/__init__.py
NoteBookForMinio/checkpoint.py
NoteBookForMinio/manager.py
NoteBookForMinio/models.py
NoteBookForMinio/test/__init__.py
NoteBookForMinio/test/test1.py
NotebookForMinio.egg-info/PKG-INFO
NotebookForMinio.egg-info/SOURCES.txt
NotebookForMinio.egg-info/dependency_links.txt
NotebookForMinio.egg-info/not-zip-safe
NotebookForMinio.egg-info/requires.txt
NotebookForMinio.egg-info/top_level.txt