Metadata-Version: 1.0
Name: NotebookForMinio
Version: 0.3.3
Summary: A Minio Driver for  ContentsManager for IPython/Jupyter.
Home-page: UNKNOWN
Author: RobertLNJ
Author-email: UNKNOWN
License: MIT
Platform: UNKNOWN
